pressurecooker/__init__.py
pressurecooker/converters.py
pressurecooker/encodings.py
pressurecooker/ie_result.py
pressurecooker/images.py
pressurecooker/proxy.py
pressurecooker/subtitles.py
pressurecooker/thumbscropping.py
pressurecooker/utils.py
pressurecooker/videos.py
pressurecooker/web.py
pressurecooker/youtube.py
tests/__init__.py
tests/test_converters.py
tests/test_proxy.py
tests/test_subtitles.py
tests/test_thumbnails.py
tests/test_videos.py
tests/test_web.py
tests/test_youtube.py
pressurecooker-0.0.29.dist-info/LICENSE
pressurecooker-0.0.29.dist-info/METADATA
pressurecooker-0.0.29.dist-info/WHEEL
pressurecooker-0.0.29.dist-info/top_level.txt
pressurecooker-0.0.29.dist-info/RECORD
