Metadata-Version: 2.1
Name: pressurecooker
Version: 0.0.29
Summary: A collection of utilities for media processing.
Home-page: https://github.com/learningequality/pressurecooker
Author: Learning Equality
Author-email: dev@learningequality.org
License: MIT license
Keywords: media,mediaprocessing,video,compression,thumbnails,pressurecooker
Platform: UNKNOWN
Classifier: Development Status :: 2 - Pre-Alpha
Classifier: Intended Audience :: Developers
Classifier: License :: OSI Approved :: MIT License
Classifier: Natural Language :: English
Classifier: Programming Language :: Python :: 2.7
Classifier: Programming Language :: Python :: 3.4
Classifier: Programming Language :: Python :: 3.5
Classifier: Programming Language :: Python :: 3.6
Classifier: Programming Language :: Python :: 3.7
Requires-Dist: ffmpy (>=0.2.2)
Requires-Dist: le-utils (>=0.1.24)
Requires-Dist: matplotlib (==2.2.3)
Requires-Dist: numpy (==1.15.4)
Requires-Dist: Pillow (==5.4.1)
Requires-Dist: youtube-dl (>=2020.3.24)
Requires-Dist: pdf2image (==1.11.0)
Requires-Dist: le-pycaption (>=2.2.0a1)
Requires-Dist: beautifulsoup4 (<4.9.0,>=4.6.3)
Requires-Dist: EbookLib (>=0.17.1)
